aiohttp_requests/__init__.py
aiohttp_requests-0.2.4.dist-info/LICENSE
aiohttp_requests-0.2.4.dist-info/METADATA
aiohttp_requests-0.2.4.dist-info/WHEEL
aiohttp_requests-0.2.4.dist-info/top_level.txt
aiohttp_requests-0.2.4.dist-info/RECORD
