Metadata-Version: 2.1
Name: aiohttp-requests
Version: 0.2.4
Summary: A thin wrapper for aiohttp client with Requests simplicity
Home-page: https://github.com/maxzheng/aiohttp-requests
Author: Max Zheng
Author-email: maxzheng.os @t gmail.com
License: MIT
Keywords: aiohttp HTTP client async requests
Classifier: Development Status :: 5 - Production/Stable
Classifier: Intended Audience :: Developers
Classifier: Topic :: Software Development :: Libraries :: Python Modules
Classifier: License :: OSI Approved :: MIT License
Classifier: Programming Language :: Python :: 3
Requires-Python: >=3.6
License-File: LICENSE
Requires-Dist: aiohttp[speedups]
Requires-Dist: coworker (==2.*)
